setup.py
untimely/__init__.py
untimely.egg-info/PKG-INFO
untimely.egg-info/SOURCES.txt
untimely.egg-info/dependency_links.txt
untimely.egg-info/top_level.txt