Metadata-Version: 1.0
Name: untimely
Version: 1.0.0
Summary: Make time measurements with ease!
Home-page: UNKNOWN
Author: Brian Lauber
Author-email: constructible.truth@gmail.com
License: UNKNOWN
Platform: UNKNOWN
